django_comma_integer_field/__init__.py
django_comma_integer_field/apps.py
django_comma_integer_field/fields.py
django_comma_integer_field/static/admin/js/comma_integer_field.js
django_comma_integer_field-1.0.0.dist-info/licenses/LICENSE
django_comma_integer_field-1.0.0.dist-info/METADATA
django_comma_integer_field-1.0.0.dist-info/WHEEL
django_comma_integer_field-1.0.0.dist-info/top_level.txt
django_comma_integer_field-1.0.0.dist-info/RECORD
